attention_map_diffusers/__init__.py
attention_map_diffusers/modules.py
attention_map_diffusers/utils.py
attention_map_diffusers-0.1.5.dist-info/LICENSE
attention_map_diffusers-0.1.5.dist-info/METADATA
attention_map_diffusers-0.1.5.dist-info/WHEEL
attention_map_diffusers-0.1.5.dist-info/top_level.txt
attention_map_diffusers-0.1.5.dist-info/RECORD
