Metadata-Version: 2.1
Name: attention_map_diffusers
Version: 0.1.5
Summary: attention map for diffusers
Home-page: https://github.com/wooyeolBaek/attention-map-diffusers
Author: wooyeolbaek
Author-email: 100wooyeol@gmail.com
Classifier: Programming Language :: Python :: 3
Classifier: License :: OSI Approved :: MIT License
Classifier: Operating System :: OS Independent
Requires-Python: >=3.7
License-File: LICENSE
Requires-Dist: diffusers>=0.29.0
Requires-Dist: accelerate
Requires-Dist: transformers
Requires-Dist: einops
Requires-Dist: torchvision
Requires-Dist: protobuf
Requires-Dist: sentencepiece
